sqlton/__init__.py
sqlton/__init__.py~
sqlton/ast.py
sqlton/ast.py~
sqlton/parser.py
sqlton/parser.py~
sqlton-0.1.19.dist-info/METADATA
sqlton-0.1.19.dist-info/WHEEL
sqlton-0.1.19.dist-info/entry_points.txt
sqlton-0.1.19.dist-info/RECORD
