Metadata-Version: 2.1
Name: sqlton
Version: 0.1.19
Summary: Parse SQL statement into straight forward Syntax Tree.
Author: Charles Bajeux
Author-email: charles.bajeux@gmail.com
Requires-Python: >=3.11,<4.0
Classifier: Programming Language :: Python :: 3
Classifier: Programming Language :: Python :: 3.11
Classifier: Programming Language :: Python :: 3.12
Requires-Dist: sly (>=0.5,<0.6)
